{
  "slug": "electoral-district-demographic-impact-modeler",
  "title": "Electoral District Demographic Impact Modeler",
  "seo": {
    "title": "Electoral District Demographic Impact Modeler | Analyze Redistricting Effects",
    "description": "Evaluate how proposed electoral district boundary changes impact voter demographics, political representation, and community cohesion. Utilize data-driven insights for redistricting analysis."
  },
  "inputs": [
    {
      "id": "currentDistrictVAP",
      "label": "Current District Voter-Age Population (VAP)",
      "type": "number",
      "placeholder": "e.g., 500000",
      "required": true,
      "step": 1
    },
    {
      "id": "proposedDistrictVAP",
      "label": "Proposed District Voter-Age Population (VAP)",
      "type": "number",
      "placeholder": "e.g., 520000",
      "required": true,
      "step": 1
    },
    {
      "id": "currentDemogA_VAP_pct",
      "label": "Current % VAP: Demographic Group A (e.g., 18-34 years)",
      "type": "number",
      "placeholder": "e.g., 25",
      "required": true,
      "step": 0.1
    },
    {
      "id": "proposedDemogA_VAP_pct",
      "label": "Proposed % VAP: Demographic Group A",
      "type": "number",
      "placeholder": "e.g., 30",
      "required": true,
      "step": 0.1
    },
    {
      "id": "currentDemogB_VAP_pct",
      "label": "Current % VAP: Demographic Group B (e.g., Specific Ethnicity)",
      "type": "number",
      "placeholder": "e.g., 35",
      "required": true,
      "step": 0.1
    },
    {
      "id": "proposedDemogB_VAP_pct",
      "label": "Proposed % VAP: Demographic Group B",
      "type": "number",
      "placeholder": "e.g., 30",
      "required": true,
      "step": 0.1
    },
    {
      "id": "demogA_HistoricalTurnout",
      "label": "Historical Turnout Rate (Decimal): Demog Group A",
      "type": "number",
      "placeholder": "e.g., 0.55 (55%)",
      "required": true,
      "step": 0.01
    },
    {
      "id": "demogA_PartyASupport",
      "label": "Party A Support Rate (Decimal): Demog Group A",
      "type": "number",
      "placeholder": "e.g., 0.60 (60%)",
      "required": true,
      "step": 0.01
    },
    {
      "id": "demogB_HistoricalTurnout",
      "label": "Historical Turnout Rate (Decimal): Demog Group B",
      "type": "number",
      "placeholder": "e.g., 0.48 (48%)",
      "required": true,
      "step": 0.01
    },
    {
      "id": "demogB_PartyASupport",
      "label": "Party A Support Rate (Decimal): Demog Group B",
      "type": "number",
      "placeholder": "e.g., 0.35 (35%)",
      "required": true,
      "step": 0.01
    }
  ],
  "outputs": [
    {
      "id": "demographicShiftIndex",
      "label": "Demographic Shift Index",
      "unit": "Index (0-100)",
      "precision": 1
    },
    {
      "id": "projectedOverallTurnoutChange",
      "label": "Projected Overall Turnout Change",
      "unit": "%",
      "precision": 2
    },
    {
      "id": "projectedPartyA_VoteShare",
      "label": "Projected Party A Vote Share",
      "unit": "%",
      "precision": 2
    },
    {
      "id": "communityCohesionImpactScore",
      "label": "Community Cohesion Impact Score",
      "unit": "(-5 to +5)",
      "precision": 1
    }
  ],
  "formula": "function calculate({ currentDistrictVAP, proposedDistrictVAP, currentDemogA_VAP_pct, proposedDemogA_VAP_pct, currentDemogB_VAP_pct, proposedDemogB_VAP_pct, demogA_HistoricalTurnout, demogA_PartyASupport, demogB_HistoricalTurnout, demogB_PartyASupport }) {\n\n    // Input Validation and Normalization\n    const validateAndNormalize = (val, min, max, defaultVal) => {\n        let num = parseFloat(val);\n        if (isNaN(num) || num < min || num > max) return defaultVal;\n        return num;\n    };\n\n    currentDistrictVAP = validateAndNormalize(currentDistrictVAP, 0, Infinity, 0);\n    proposedDistrictVAP = validateAndNormalize(proposedDistrictVAP, 0, Infinity, 0);\n\n    let currentDemogA_VAP_pct_norm = validateAndNormalize(currentDemogA_VAP_pct, 0, 100, 0) / 100;\n    let proposedDemogA_VAP_pct_norm = validateAndNormalize(proposedDemogA_VAP_pct, 0, 100, 0) / 100;\n    let currentDemogB_VAP_pct_norm = validateAndNormalize(currentDemogB_VAP_pct, 0, 100, 0) / 100;\n    let proposedDemogB_VAP_pct_norm = validateAndNormalize(proposedDemogB_VAP_pct, 0, 100, 0) / 100;\n\n    demogA_HistoricalTurnout = validateAndNormalize(demogA_HistoricalTurnout, 0, 1, 0);\n    demogA_PartyASupport = validateAndNormalize(demogA_PartyASupport, 0, 1, 0);\n    demogB_HistoricalTurnout = validateAndNormalize(demogB_HistoricalTurnout, 0, 1, 0);\n    demogB_PartyASupport = validateAndNormalize(demogB_PartyASupport, 0, 1, 0);\n\n    // Handle cases where total specified percentages exceed 100 for robustness\n    const currentSumPct = currentDemogA_VAP_pct_norm + currentDemogB_VAP_pct_norm;\n    const proposedSumPct = proposedDemogA_VAP_pct_norm + proposedDemogB_VAP_pct_norm;\n\n    if (currentSumPct > 1) {\n        const scale = 1 / currentSumPct;\n        currentDemogA_VAP_pct_norm *= scale;\n        currentDemogB_VAP_pct_norm *= scale;\n    }\n    if (proposedSumPct > 1) {\n        const scale = 1 / proposedSumPct;\n        proposedDemogA_VAP_pct_norm *= scale;\n        proposedDemogB_VAP_pct_norm *= scale;\n    }\n\n    const currentDemogOther_VAP_pct = Math.max(0, 1 - (currentDemogA_VAP_pct_norm + currentDemogB_VAP_pct_norm));\n    const proposedDemogOther_VAP_pct = Math.max(0, 1 - (proposedDemogA_VAP_pct_norm + proposedDemogB_VAP_pct_norm));\n\n    // Assume 'Other' group's characteristics are an average of A and B, or default if A+B are zero\n    const otherDemographicsHistoricalTurnout = (demogA_HistoricalTurnout + demogB_HistoricalTurnout) / 2 || 0.5; // Default to 50%\n    const otherDemographicsPartyASupport = (demogA_PartyASupport + demogB_PartyASupport) / 2 || 0.5; // Default to 50%\n\n    // If no population data, return zeros\n    if (currentDistrictVAP === 0 && proposedDistrictVAP === 0) {\n      return {\n        demographicShiftIndex: 0,\n        projectedOverallTurnoutChange: 0,\n        projectedPartyA_VoteShare: 0,\n        communityCohesionImpactScore: 0\n      };\n    }\n\n    // Output 1: Demographic Shift Index (0-100)\n    const shiftA = Math.abs(proposedDemogA_VAP_pct_norm - currentDemogA_VAP_pct_norm);\n    const shiftB = Math.abs(proposedDemogB_VAP_pct_norm - currentDemogB_VAP_pct_norm);\n    const shiftOther = Math.abs(proposedDemogOther_VAP_pct - currentDemogOther_VAP_pct);\n    const demographicShiftIndex = Math.min(100, (shiftA + shiftB + shiftOther) * 100 / 2); // Sum of absolute differences for each group. Divide by 2 as each shift is 'counted' twice for a total change of up to 200% if one group completely replaces another. Scale to 100%.\n\n    // Output 2: Projected Overall Turnout Change\n    const calculateProjectedTurnout = (vap, demogA_pct, demogB_pct, demogOther_pct) => {\n        if (vap <= 0) return 0;\n        const turnoutA = vap * demogA_pct * demogA_HistoricalTurnout;\n        const turnoutB = vap * demogB_pct * demogB_HistoricalTurnout;\n        const turnoutOther = vap * demogOther_pct * otherDemographicsHistoricalTurnout;\n        return turnoutA + turnoutB + turnoutOther;\n    };\n\n    const currentProjectedTurnout = calculateProjectedTurnout(\n        currentDistrictVAP,\n        currentDemogA_VAP_pct_norm,\n        currentDemogB_VAP_pct_norm,\n        currentDemogOther_VAP_pct\n    );\n    const proposedProjectedTurnout = calculateProjectedTurnout(\n        proposedDistrictVAP,\n        proposedDemogA_VAP_pct_norm,\n        proposedDemogB_VAP_pct_norm,\n        proposedDemogOther_VAP_pct\n    );\n\n    let projectedOverallTurnoutChange = 0;\n    if (currentProjectedTurnout > 0) {\n        projectedOverallTurnoutChange = ((proposedProjectedTurnout - currentProjectedTurnout) / currentProjectedTurnout) * 100;\n    } else if (proposedProjectedTurnout > 0) {\n        projectedOverallTurnoutChange = Infinity; // Infinite increase from zero turnout\n    }\n\n    // Output 3: Projected Party A Vote Share\n    let projectedPartyA_VoteShare = 0;\n    if (proposedProjectedTurnout > 0) {\n        const partyAVotesA = proposedDistrictVAP * proposedDemogA_VAP_pct_norm * demogA_HistoricalTurnout * demogA_PartyASupport;\n        const partyAVotesB = proposedDistrictVAP * proposedDemogB_VAP_pct_norm * demogB_HistoricalTurnout * demogB_PartyASupport;\n        const partyAVotesOther = proposedDistrictVAP * proposedDemogOther_VAP_pct * otherDemographicsHistoricalTurnout * otherDemographicsPartyASupport;\n        const totalPartyAVotes = partyAVotesA + partyAVotesB + partyAVotesOther;\n        projectedPartyA_VoteShare = (totalPartyAVotes / proposedProjectedTurnout) * 100;\n    }\n\n    // Output 4: Community Cohesion Impact Score (-5 to +5)\n    let communityCohesionImpactScore = 0;\n    const MAX_SCORE = 5;\n\n    // Factor 1: Demographic Shift Magnitude (Higher shift index implies lower cohesion)\n    // Score impact is stronger for larger shifts.\n    communityCohesionImpactScore -= (demographicShiftIndex / 100) * (MAX_SCORE * 0.7); // Up to 70% of max negative score\n\n    // Factor 2: Significant VAP change might suggest fragmentation\n    if (currentDistrictVAP > 0) {\n        const vapChangeRatio = Math.abs(proposedDistrictVAP - currentDistrictVAP) / currentDistrictVAP;\n        if (vapChangeRatio > 0.20) { // More than 20% VAP change\n            // Larger changes lead to more negative impact, scaled up to 30% of max negative score\n            communityCohesionImpactScore -= Math.min(MAX_SCORE * 0.3, (vapChangeRatio - 0.20) * (MAX_SCORE * 0.5)); \n        }\n    }\n\n    // Factor 3: Extreme shift in a single demographic group\n    const maxIndividualDemogShift = Math.max(shiftA, shiftB, shiftOther);\n    if (maxIndividualDemogShift > 0.20) { // If one group shifts by more than 20% of VAP\n        // Additional negative impact for very large single-group shifts, up to 20% of max negative score\n        communityCohesionImpactScore -= Math.min(MAX_SCORE * 0.2, (maxIndividualDemogShift - 0.20) * (MAX_SCORE * 0.8));\n    }\n\n    // Cap the score between -5 and +5\n    communityCohesionImpactScore = Math.max(-MAX_SCORE, Math.min(MAX_SCORE, communityCohesionImpactScore));\n    // If the demographic shift index is very low, make cohesion score positive or neutral\n    if (demographicShiftIndex < 5 && vapChangeRatio < 0.05) {\n        communityCohesionImpactScore = Math.max(0, communityCohesionImpactScore); // At least 0 if very stable\n    }\n    \n    // A perfect score of 0 demographic shift and VAP stability should lead to a higher cohesion score\n    if (demographicShiftIndex === 0 && currentDistrictVAP === proposedDistrictVAP) {\n      communityCohesionImpactScore = MAX_SCORE; // Max positive if no change at all\n    }\n\n    return {\n        demographicShiftIndex: demographicShiftIndex,\n        projectedOverallTurnoutChange: projectedOverallTurnoutChange,\n        projectedPartyA_VoteShare: projectedPartyA_VoteShare,\n        communityCohesionImpactScore: communityCohesionImpactScore\n    };\n}",
  "summary": "This advanced calculator models the potential shifts in voter demographics, political party representation, and community cohesion resulting from proposed electoral district boundary changes. Inspired by real-world redistricting challenges, it provides quantitative insights to inform policy, advocacy, and strategic planning.",
  "cta": "Analyze Your Electoral District Changes",
  "faq": [
    {
      "q": "What is the primary purpose of the Electoral District Demographic Impact Modeler?",
      "a": "This tool is designed to quantitatively assess the potential consequences of proposed electoral district boundary changes. It models how voter demographics, projected voter turnout, political party representation, and a heuristic measure of community cohesion might be impacted, providing crucial insights for policymakers, advocates, and researchers."
    },
    {
      "q": "How does this tool handle complex demographic data?",
      "a": "The model simplifies demographic complexity by allowing users to define and input data for specific demographic groups (e.g., age cohorts, ethnic groups, socioeconomic segments) and an 'Other' category. While it doesn't process raw census data directly, it uses your specified percentages, historical turnout, and party support rates for these groups to project overall impacts."
    },
    {
      "q": "Is this tool useful for identifying gerrymandering?",
      "a": "While this tool doesn't explicitly 'detect' gerrymandering, it provides critical metrics that can *inform* such an analysis. By quantifying demographic shifts, turnout changes, and partisan advantage, it can highlight proposals that significantly alter electoral outcomes or fragment communities, which are common indicators of gerrymandered maps. It serves as a powerful analytical aid for those examining the fairness and representativeness of district maps."
    },
    {
      "q": "What are the limitations of the Community Cohesion Impact Score?",
      "a": "The Community Cohesion Impact Score is a heuristic metric, meaning it's based on a set of defined rules and assumptions rather than direct sociological measurement. It primarily reacts to the magnitude of demographic shifts and significant changes in voter-age population. It doesn't account for intangible cultural ties, shared local identity, or specific geographic barriers, and should be interpreted as an indicator of potential disruption rather than a definitive sociological assessment."
    },
    {
      "q": "Can I use this tool for local or state-level districts, or just national ones?",
      "a": "Yes, this tool is versatile and can be applied to electoral districts at any level of government – federal (congressional), state legislative, county, or municipal. The principles of demographic impact on electoral outcomes are consistent across different scales, provided you have the relevant voter-age population, demographic percentages, and historical voting data for your specific local or state context."
    },
    {
      "q": "How accurate are the turnout and vote share projections?",
      "a": "The accuracy of projections heavily depends on the quality and reliability of your input data, particularly the historical turnout rates and party support percentages for each demographic group. The model assumes these historical patterns will largely hold true. Unforeseen events, highly charismatic candidates, shifts in political sentiment, or significant voter mobilization efforts can introduce variability not captured by historical averages. The outputs are best viewed as informed estimates under specified conditions."
    },
    {
      "q": "What kind of input data do I need to use this tool effectively?",
      "a": "To use the tool effectively, you'll need: 1) The current and proposed Voter-Age Population (VAP) for the district; 2) The percentage breakdown of your defined demographic groups within both the current and proposed VAP; 3) Historical average voter turnout rates for each demographic group; and 4) Historical average support rates for a specific political party (Party A) among each demographic group."
    },
    {
      "q": "How does this tool define 'demographic group'?",
      "a": "The tool allows you to define 'demographic group' based on your specific analytical needs. Common definitions include age cohorts (e.g., 18-34, 35-64, 65+), racial or ethnic categories, income levels, educational attainment, or even geographic sub-regions within a larger district. The important aspect is that you consistently apply your chosen definitions for both the current and proposed district configurations and have corresponding historical data."
    }
  ],
  "tags": [
    "redistricting",
    "gerrymandering",
    "elections",
    "demographics",
    "political science",
    "policy analysis",
    "voter turnout",
    "community planning",
    "public policy",
    "data modeling"
  ],
  "related": [
    "voter-registration-rate-predictor",
    "election-turnout-forecaster",
    "legislative-impact-analyzer",
    "district-fairness-index"
  ],
  "article": [
    {
      "heading": "The Importance of Electoral District Demographic Impact Modeler in Modern Context",
      "body": "The landscape of political representation is fundamentally shaped by the drawing of electoral district boundaries. While often perceived as a technical exercise, redistricting is inherently a profoundly political process with far-reaching consequences for how communities are represented, whose voices are amplified, and ultimately, who holds power. The recent case of Virginia's proposed 10-1 congressional map serves as a stark reminder of this reality. Such plans are not merely lines on a map; they are strategic decisions that can drastically alter the demographic composition of a district, subsequently influencing voter turnout, partisan leanings, and the overall political outcomes for years, if not decades. This is precisely where the Electoral District Demographic Impact Modeler becomes an indispensable tool.\n\nIn an increasingly data-driven world, reliance on intuition or anecdotal evidence in such a high-stakes arena is no longer sufficient. Modern redistricting debates demand rigorous analysis that can quantify the complex interplay between geographic shifts, demographic changes, and electoral results. The 'why' behind this tool is multifaceted: it addresses the need for transparency, enables proactive strategic planning, and facilitates academic and journalistic scrutiny of redistricting proposals. Without objective methods to model these impacts, the process risks becoming opaque and susceptible to manipulation, undermining the very principles of fair and equitable representation.\n\nElectoral districts are not just administrative units; they are designed to give a voice to communities. When these boundaries are redrawn, existing communities can be fractured, leading to a dilution of collective power and a weakening of local identity. Conversely, new districts can be forged that empower previously underrepresented groups. The demographic shifts caused by redistricting—whether intentional or unintentional—can dramatically alter the proportion of different age groups, ethnicities, socio-economic classes, or political affiliations within a district. These shifts directly correlate with changes in voter eligibility, registration rates, historical turnout patterns, and ultimately, which candidates and parties are likely to succeed.\n\nFurthermore, the impact extends beyond raw election results. Redistricting can influence public policy and resource allocation. A district with a new demographic profile might prioritize different issues, from infrastructure development to educational funding. Therefore, understanding these demographic consequences allows urban planners, community advocates, and civil rights organizations to anticipate and respond to the changing needs and political leverage of their constituents. The Electoral District Demographic Impact Modeler empowers stakeholders with the analytical insights necessary to navigate these intricate political terrains, promoting more informed discussions and advocating for maps that truly serve the public interest rather than narrow partisan goals."
    },
    {
      "heading": "In-Depth Technical Guide: How the Calculation Works",
      "body": "The Electoral District Demographic Impact Modeler operates on a series of interconnected calculations designed to provide a comprehensive assessment of redistricting proposals. Each output is derived from logical steps, transforming raw input data into actionable insights.\n\n**1. Input Validation and Normalization:** Before any calculations begin, all user inputs undergo validation. This ensures that numerical values are within reasonable bounds (e.g., percentages between 0-100, populations are non-negative). Importantly, demographic percentages are normalized internally to ensure they sum up to 100%, and an 'Other' demographic group is dynamically calculated to account for any remaining population not explicitly assigned to Group A or B. This provides a robust base for subsequent steps, mitigating errors from incomplete or inconsistent user data.\n\n**2. Demographic Shift Index Calculation:** This output quantifies the overall magnitude of demographic change between the current and proposed district configurations. It is calculated by summing the absolute differences in the percentage of Voter-Age Population (VAP) for each demographic group (Group A, Group B, and 'Other') between the two district layouts. For example, if Group A changes from 25% to 30%, that's an absolute difference of 5%. By summing these absolute differences for all groups and normalizing to a scale of 0-100, the index provides a clear, single metric representing the total demographic 'churn' or transformation within the district. A higher index indicates a more significant demographic alteration.\n\n**3. Projected Overall Turnout (Current and Proposed):** To determine how voter turnout might change, the model first estimates the total number of likely voters for both the current and proposed districts. This involves multiplying the Voter-Age Population (VAP) of the district by the percentage of each demographic group within that VAP, and then by the historical turnout rate specific to that group. For example, `(District VAP * % Demog A in VAP * Historical Turnout Rate Demog A)`. This is done for all defined demographic groups, and the results are summed to yield the total projected turnout. The historical turnout rates are crucial here, as different demographic groups often exhibit distinct participation patterns. The 'Other' group's turnout rate is an averaged default, but in a more advanced model, this would be user-defined.\n\n**4. Projected Overall Turnout Change:** Once the current and proposed projected turnouts are calculated, the percentage change is straightforward: `((Proposed Projected Turnout - Current Projected Turnout) / Current Projected Turnout) * 100`. This metric highlights whether a proposed map is likely to increase or decrease the overall number of votes cast, which can have significant implications for campaign strategies and democratic participation.\n\n**5. Projected Party A Vote Share:** This calculation aims to predict the electoral fortunes of a specific political party (Party A, as defined by the user's input). It involves a weighted average of Party A's support across all demographic groups, factoring in their projected turnout. For each demographic group in the *proposed* district, the model calculates the number of likely voters for Party A: `(Proposed District VAP * % Demog A in VAP * Demog A Historical Turnout * Demog A Party A Support)`. These individual group contributions are summed to get the total projected votes for Party A. This sum is then divided by the `Proposed Projected Turnout` (total likely votes in the new district) and multiplied by 100 to yield a percentage vote share for Party A. This provides a direct indication of how the new district boundaries might shift partisan advantage.\n\n**6. Community Cohesion Impact Score:** This is a heuristic measure, meaning it's based on a set of logical rules and assumptions to estimate a complex, qualitative concept. The score, ranging from -5 to +5, assesses potential disruption to community cohesion. It is influenced by three main factors: \n    *   **Demographic Shift Magnitude:** A higher `Demographic Shift Index` (meaning more significant changes in the composition of demographic groups) contributes negatively to cohesion. The intuition here is that rapid or substantial shifts in a district's population makeup can strain existing social structures and shared identities. \n    *   **Significant VAP Change:** If the `proposedDistrictVAP` differs substantially (e.g., by more than 20%) from the `currentDistrictVAP` without a proportionally balanced demographic redistribution, it may suggest the district is being radically reconfigured, potentially splitting existing communities or merging disparate ones. This factor also contributes negatively to the score.\n    *   **Extreme Individual Demographic Shifts:** If any single demographic group experiences a particularly large shift in its percentage of the VAP (e.g., more than 20%), it further impacts the score negatively. This flags instances where a district might be 'packed' or 'cracked' to consolidate or dilute a particular group's voting power, which often corresponds with reduced community cohesion. \n\nThe individual impacts are weighted and summed, with the final score capped between -5 (highly negative impact on cohesion) and +5 (minimal to no negative impact, or even a slight positive if shifts are negligible). It's important to remember this is an *indicator* and not a definitive sociological measure, reflecting the model's attempt to quantify a nuanced social effect based on available numerical inputs."
    },
    {
      "heading": "Real-World Application Scenarios",
      "body": "The Electoral District Demographic Impact Modeler is a versatile tool with profound applications across various sectors, enabling data-driven decision-making in the complex world of political redistricting. Here are a few detailed scenarios illustrating its utility:\n\n**Scenario 1: The Political Campaign Strategist**\nImagine Sarah, a campaign manager for a congressional candidate in a state undergoing redistricting. A new map proposal has just been released, and her candidate's district boundaries are significantly altered. Sarah's primary concern is to understand how these changes will affect her candidate's chances of winning the next election. She uses the Impact Modeler by inputting the current and proposed Voter-Age Populations (VAP) for the district. For demographic groups (e.g., young professionals, suburban families, rural voters), she inputs their estimated percentages in both the old and new districts, along with historical turnout rates and their typical support for her candidate's party. The model quickly reveals a projected decrease in overall voter turnout by 3% and a 5-point drop in her candidate's projected vote share. This immediate insight tells Sarah that the new map is disadvantageous. She can then drill down: is the drop due to a decrease in a high-turnout, supportive demographic, or an influx of a low-turnout, opposition-leaning group? With this data, Sarah can adjust her campaign strategy, focusing on increased voter registration and mobilization efforts in newly incorporated areas, or re-allocating resources to high-potential precincts to counteract the adverse demographic shifts. She might also use the tool to compare multiple proposed maps, identifying the least harmful or even beneficial option for her candidate.\n\n**Scenario 2: The Urban Planner & Community Advocate**\nDavid is an urban planner and a passionate community advocate in a diverse metropolitan area. His city council district is facing a redrawing of lines that appears to split a historically cohesive immigrant community into two separate districts. David fears this will dilute their collective voting power and make it harder for the community to elect representatives who understand their unique needs. He gathers VAP data and estimates the percentage of his target immigrant community in both the current and proposed districts. He also inputs turnout rates and their general political preferences. The Impact Modeler returns a high 'Demographic Shift Index' for both affected districts and a significantly negative 'Community Cohesion Impact Score.' Furthermore, the projected vote share for candidates typically supported by this community drops in both fragmented districts. Armed with these quantitative results, David can present compelling evidence to the redistricting commission. He can argue, with data, that the proposed map actively harms community cohesion and dilutes minority representation, rather than simply stating it as an opinion. This data can be pivotal in rallying local support, informing media narratives, and pushing for alternative maps that keep his community intact.\n\n**Scenario 3: The Academic Researcher/Policy Analyst**\nDr. Anya Sharma is a political scientist researching the long-term effects of redistricting on political polarization and minority representation across states. She uses the Electoral District Demographic Impact Modeler as a core component of her research methodology. For various states and historical redistricting cycles, she feeds the model with demographic data (e.g., racial composition, age distribution) before and after redistricting events, along with historical election data. By running numerous simulations, Dr. Sharma can quantify the `Demographic Shift Index` and `Projected Party A Vote Share` for hundreds of districts. This allows her to identify patterns where specific demographic changes consistently lead to shifts in partisan control or to the marginalization of certain groups. She might discover, for example, that districts with a high `Demographic Shift Index` after redistricting tend to experience higher rates of political incumbent defeat, or that certain types of demographic shifts correlate with increased political homogeneity within districts. Her findings, backed by the rigorous modeling from this tool, contribute to academic literature and inform national policy debates on electoral reform and fairness in redistricting."
    },
    {
      "heading": "Advanced Considerations and Potential Pitfalls",
      "body": "While the Electoral District Demographic Impact Modeler provides powerful insights, its effective use necessitates an understanding of its inherent limitations and advanced considerations. No model is a perfect predictor, and the complexities of human behavior and political systems introduce several nuances.\n\n**1. Data Accuracy and Granularity:** The 'Garbage In, Garbage Out' (GIGO) principle is profoundly relevant here. The model's outputs are only as reliable as the input data. Inaccurate VAP counts, outdated demographic percentages, or flawed historical turnout and party support rates will lead to misleading results. Furthermore, the granularity of demographic groups matters. Aggregating diverse populations into broad categories (e.g., 'all non-white voters') might obscure important internal variations in turnout and political preference. Users should strive for the most precise and disaggregated data available, while also acknowledging potential biases in data collection.\n\n**2. Dynamic Voter Behavior and External Factors:** The model assumes that historical voter behavior (turnout and party support by demographic group) will largely persist in the proposed district. However, voter behavior is dynamic. The salience of specific issues, the charisma of particular candidates, national political trends, unprecedented campaign spending, or unforeseen events (e.g., a major economic downturn or a public health crisis) can significantly alter turnout and voting patterns, overriding historical averages. The model provides a 'snapshot' under historical conditions, and users must apply critical judgment regarding how current events might deviate from these baselines.\n\n**3. Limitations of the Community Cohesion Impact Score:** As a heuristic, the Community Cohesion Impact Score offers a simplified representation of a deeply complex sociological phenomenon. 'Community cohesion' involves shared values, social networks, cultural practices, geographic proximity, and a sense of belonging—factors that are difficult, if not impossible, to quantify purely through demographic shifts. The score identifies *potential* areas of concern based on numerical changes but cannot capture the nuances of existing community bonds or the resilience of local groups. It should serve as a prompt for further qualitative research and local engagement rather than a definitive statement.\n\n**4. Ethical Implications and Potential for Misuse:** Tools that quantify political impact, including this model, carry ethical responsibilities. While designed for transparency and fair analysis, such models could theoretically be reverse-engineered or used to optimize gerrymandering efforts—that is, to draw maps that unfairly benefit one political party or group over others. It is incumbent upon users to wield these insights responsibly, prioritizing principles of fair representation, equal access, and democratic integrity. The transparency of the model's calculations is intended to facilitate scrutiny, not enable manipulation.\n\n**5. Unaccounted Variables:** The model focuses primarily on demographic shifts, turnout, and partisan preference. However, other critical factors influence elections and district dynamics that are not explicitly modeled. These can include incumbent advantage, campaign finance disparities, media coverage, grassroots organizing effectiveness, the number and strength of competing candidates, and the overall political climate. While some of these might indirectly influence historical turnout or support rates, their direct impact is not isolated or calculated by the tool. A holistic analysis would integrate these broader considerations alongside the model's outputs.\n\nBy being mindful of these advanced considerations and potential pitfalls, users can leverage the Electoral District Demographic Impact Modeler as a powerful and responsible instrument for understanding and shaping the future of democratic representation."
    }
  ]
}
