{
  "slug": "student-aid-eligibility-optimizer",
  "title": "Student Aid Eligibility Optimizer",
  "seo": {
    "title": "Student Aid Eligibility Optimizer | Maximize College Financial Aid",
    "description": "Estimate and optimize your eligibility for student grants, scholarships, and federal loans. Our optimizer helps families understand financial aid potential based on income, assets, and academic profiles for better college financial planning."
  },
  "inputs": [
    {
      "id": "costOfAttendance",
      "label": "Estimated Cost of Attendance (COA)",
      "type": "number",
      "placeholder": "e.g., 35000",
      "required": true,
      "step": 500
    },
    {
      "id": "parentAgi",
      "label": "Parent(s) Adjusted Gross Income (AGI)",
      "type": "number",
      "placeholder": "e.g., 85000",
      "required": true,
      "step": 1000
    },
    {
      "id": "studentAgi",
      "label": "Student's Adjusted Gross Income (AGI)",
      "type": "number",
      "placeholder": "e.g., 2500",
      "required": true,
      "step": 100
    },
    {
      "id": "parentAssets",
      "label": "Parent(s) Non-Retirement Assets (Cash, Savings, Investments)",
      "type": "number",
      "placeholder": "e.g., 50000",
      "required": true,
      "step": 1000
    },
    {
      "id": "studentAssets",
      "label": "Student's Non-Retirement Assets (Cash, Savings, Investments)",
      "type": "number",
      "placeholder": "e.g., 3000",
      "required": true,
      "step": 100
    },
    {
      "id": "familySize",
      "label": "Number of People in Household",
      "type": "number",
      "placeholder": "e.g., 4",
      "required": true,
      "step": 1
    },
    {
      "id": "collegeStudents",
      "label": "Number of College Students in Household (including applicant)",
      "type": "number",
      "placeholder": "e.g., 1",
      "required": true,
      "step": 1
    },
    {
      "id": "isDependent",
      "label": "Is the Student a Dependent?",
      "type": "text",
      "placeholder": "Yes / No",
      "required": true
    },
    {
      "id": "gpa",
      "label": "Student's GPA (on a 4.0 scale)",
      "type": "number",
      "placeholder": "e.g., 3.75",
      "required": true,
      "step": 0.01
    },
    {
      "id": "satActScore",
      "label": "Student's SAT/ACT Score (Optional)",
      "type": "number",
      "placeholder": "e.g., 1350 (SAT) or 28 (ACT)",
      "required": false,
      "step": 10
    }
  ],
  "outputs": [
    {
      "id": "expectedFamilyContribution",
      "label": "Estimated Expected Family Contribution (EFC)",
      "unit": "$",
      "precision": 0
    },
    {
      "id": "financialNeed",
      "label": "Calculated Financial Need",
      "unit": "$",
      "precision": 0
    },
    {
      "id": "maxFederalPellGrant",
      "label": "Estimated Federal Pell Grant Eligibility",
      "unit": "$",
      "precision": 0
    },
    {
      "id": "maxFederalStudentLoan",
      "label": "Estimated Max Federal Student Loan Eligibility",
      "unit": "$",
      "precision": 0
    },
    {
      "id": "meritScholarshipPotential",
      "label": "Estimated Merit Scholarship Potential",
      "unit": "$",
      "precision": 0
    },
    {
      "id": "totalAidEligibility",
      "label": "Total Estimated Aid Eligibility",
      "unit": "$",
      "precision": 0
    }
  ],
  "formula": "function calculate(inputs) {\n    // Constants (simplified, based on general FAFSA principles, not actual year-specific tables)\n    // These values are illustrative and would be updated annually for a production tool.\n    const PARENT_INCOME_PROTECTION_BASE = 19500; // For one parent, scaled by family size\n    const PARENT_INCOME_PROTECTION_PER_ADDITIONAL = 6000;\n    const STUDENT_INCOME_PROTECTION = 7600; // Approx 2023-24 value\n    const PARENT_ASSET_PROTECTION_BASE = 26000; // For dependent, scales roughly with family size/age\n    const PARENT_ASSET_CONTRIBUTION_RATE = 0.0564; // Approx FAFSA rate\n    const STUDENT_ASSET_CONTRIBUTION_RATE = 0.20; // Approx FAFSA rate\n    const PARENT_INCOME_CONTRIBUTION_RATE_TIERS = [\n        { threshold: 30000, rate: 0.22 },\n        { threshold: 60000, rate: 0.30 },\n        { threshold: 90000, rate: 0.38 },\n        { threshold: Infinity, rate: 0.47 } // Final tier catches all above\n    ];\n    const STUDENT_INCOME_CONTRIBUTION_RATE = 0.50;\n\n    const MAX_PELL_GRANT = 7395; // Approx 2023-24 value for EFC=0\n    const PELL_EFC_THRESHOLD = 7000; // EFC value above which Pell typically phases out, simplified.\n\n    // Federal Student Loan Caps (simplified for dependent undergraduates, 1st year)\n    const LOAN_CAPS = {\n        '1stYear': { subsidized: 3500, unsubsidized: 2000 },\n        '2ndYear': { subsidized: 4500, unsubsidized: 2000 },\n        '3rdYear+': { subsidized: 5500, unsubsidized: 2000 }\n    };\n\n    // Merit Scholarship Potential (simplified scale)\n    const MERIT_GPA_TIERS = [\n        { gpa: 4.0, potential: 15000 },\n        { gpa: 3.8, potential: 10000 },\n        { gpa: 3.5, potential: 6000 },\n        { gpa: 3.0, potential: 2000 },\n        { gpa: 2.5, potential: 500 },\n        { gpa: 0, potential: 0 } // Base case\n    ];\n    const MERIT_SAT_FACTOR = 0.02; // Additional $ per point above 1000 SAT\n    const MERIT_ACT_FACTOR = 150; // Additional $ per point above 20 ACT\n\n    const INSTITUTIONAL_GRANT_FACTOR = 0.25; // Estimate 25% of remaining need might be covered by institutional grants\n\n    const {\n        parentAgi,\n        studentAgi,\n        parentAssets,\n        studentAssets,\n        familySize,\n        collegeStudents,\n        isDependent,\n        gpa,\n        satActScore,\n        costOfAttendance\n    } = inputs;\n\n    let expectedFamilyContribution = 0;\n    let financialNeed = 0;\n    let maxFederalPellGrant = 0;\n    let maxFederalStudentLoan = 0;\n    let meritScholarshipPotential = 0;\n    let totalAidEligibility = 0;\n\n    const isStudentDependent = (isDependent === \"Yes\");\n    const actualCollegeStudents = Math.max(1, collegeStudents); // Ensure at least 1 for division\n    const studentGpa = parseFloat(gpa) || 0;\n    const studentSatActScore = parseInt(satActScore) || 0; // Handle optional SAT/ACT\n\n    // --- 1. Expected Family Contribution (EFC) Calculation (Simplified FAFSA-like logic) ---\n\n    let parentContributionTotal = 0;\n    if (isStudentDependent) {\n        // Parent Income Protection Allowance (IPA)\n        const parentIPA = PARENT_INCOME_PROTECTION_BASE + (Math.max(0, familySize - 1) * PARENT_INCOME_PROTECTION_PER_ADDITIONAL);\n        const parentDisposableIncome = Math.max(0, parentAgi - parentIPA);\n\n        // Parent Income Contribution (Simplified Tiered Calculation)\n        let parentIncomeContribution = 0;\n        if (parentDisposableIncome > 0) {\n            let currentIncome = parentDisposableIncome;\n            let accumulatedIncomeFromPreviousTiers = 0;\n            for (const tier of PARENT_INCOME_CONTRIBUTION_RATE_TIERS) {\n                if (currentIncome <= 0) break;\n                const incomeInThisTier = Math.min(currentIncome, tier.threshold === Infinity ? currentIncome : (tier.threshold - accumulatedIncomeFromPreviousTiers));\n                parentIncomeContribution += incomeInThisTier * tier.rate;\n                currentIncome -= incomeInThisTier;\n                accumulatedIncomeFromPreviousTiers += incomeInThisTier;\n            }\n        }\n\n        // Parent Asset Protection Allowance (APA)\n        const parentAPA = PARENT_ASSET_PROTECTION_BASE + (Math.max(0, familySize - 2) * 5000); // Simplified scaling\n        const parentNetAssets = Math.max(0, parentAssets - parentAPA);\n        const parentAssetContribution = parentNetAssets * PARENT_ASSET_CONTRIBUTION_RATE;\n\n        parentContributionTotal = parentIncomeContribution + parentAssetContribution;\n        // Divide parental contribution by number of college students (this lowers per-student EFC)\n        parentContributionTotal /= actualCollegeStudents;\n    }\n\n    // Student Income Contribution (SIC)\n    const studentDisposableIncome = Math.max(0, studentAgi - STUDENT_INCOME_PROTECTION);\n    const studentIncomeContribution = studentDisposableIncome * STUDENT_INCOME_CONTRIBUTION_RATE;\n\n    // Student Asset Contribution (SAC)\n    const studentAssetContribution = studentAssets * STUDENT_ASSET_CONTRIBUTION_RATE;\n\n    expectedFamilyContribution = parentContributionTotal + studentIncomeContribution + studentAssetContribution;\n    expectedFamilyContribution = Math.max(0, Math.round(expectedFamilyContribution));\n\n    // --- 2. Financial Need Calculation ---\n    financialNeed = Math.max(0, costOfAttendance - expectedFamilyContribution);\n\n    // --- 3. Federal Pell Grant ---\n    if (expectedFamilyContribution <= 0) {\n        maxFederalPellGrant = MAX_PELL_GRANT;\n    } else if (expectedFamilyContribution < PELL_EFC_THRESHOLD) {\n        maxFederalPellGrant = MAX_PELL_GRANT * (1 - (expectedFamilyContribution / PELL_EFC_THRESHOLD));\n    } else {\n        maxFederalPellGrant = 0;\n    }\n    maxFederalPellGrant = Math.round(Math.max(0, maxFederalPellGrant));\n\n    // --- 4. Federal Student Loan Eligibility ---\n    // Assuming 1st-year undergraduate. In a real system, student's year would be an input.\n    let currentLoanCaps = LOAN_CAPS['1stYear'];\n    if (!isStudentDependent) {\n        currentLoanCaps = { subsidized: 0, unsubsidized: 6000 }; // Example for independent, first year\n    }\n\n    let potentialSubsidizedLoan = Math.min(currentLoanCaps.subsidized, financialNeed);\n    let potentialUnsubsidizedLoan = currentLoanCaps.unsubsidized;\n\n    // Subsidized loan cannot exceed remaining need after other grant aid (like Pell)\n    let remainingNeedForSubsidized = Math.max(0, financialNeed - maxFederalPellGrant);\n    potentialSubsidizedLoan = Math.min(potentialSubsidizedLoan, remainingNeedForSubsidized);\n\n    // Unsubsidized loan can cover up to COA minus other aid (EFC + Pell + Subsidized Loan)\n    let maxUnsubsidizedBasedOnCOA = Math.max(0, costOfAttendance - expectedFamilyContribution - maxFederalPellGrant - potentialSubsidizedLoan);\n    potentialUnsubsidizedLoan = Math.min(potentialUnsubsidizedLoan, maxUnsubsidizedBasedOnCOA);\n\n    maxFederalStudentLoan = potentialSubsidizedLoan + potentialUnsubsidizedLoan;\n    maxFederalStudentLoan = Math.round(Math.max(0, maxFederalStudentLoan));\n\n    // --- 5. Merit Scholarship Potential ---\n    let meritFromGpa = 0;\n    for (const tier of MERIT_GPA_TIERS) {\n        if (studentGpa >= tier.gpa) {\n            meritFromGpa = tier.potential;\n            break;\n        }\n    }\n\n    let meritFromSatAct = 0;\n    if (studentSatActScore) {\n        if (studentSatActScore >= 400 && studentSatActScore <= 1600) { // Assume SAT\n            meritFromSatAct = Math.max(0, (studentSatActScore - 1000)) * MERIT_SAT_FACTOR;\n        } else if (studentSatActScore >= 1 && studentSatActScore <= 36) { // Assume ACT\n            meritFromSatAct = Math.max(0, (studentSatActScore - 20)) * MERIT_ACT_FACTOR;\n        }\n    }\n    meritScholarshipPotential = Math.round(meritFromGpa + meritFromSatAct);\n    // Cap merit scholarship at a reasonable percentage of COA, e.g., 50%\n    meritScholarshipPotential = Math.min(meritScholarshipPotential, costOfAttendance * 0.5);\n\n    // --- 6. Total Estimated Aid Eligibility ---\n    // Includes Pell, Federal Loans, Merit, and a simplified estimate for institutional need-based grants\n    let institutionalGrantPotential = Math.max(0, financialNeed - maxFederalPellGrant - potentialSubsidizedLoan); // Need not covered by Pell or subsidized loans\n    institutionalGrantPotential = Math.round(institutionalGrantPotential * INSTITUTIONAL_GRANT_FACTOR);\n    institutionalGrantPotential = Math.min(institutionalGrantPotential, financialNeed); // Institutional grants should not exceed need\n\n    totalAidEligibility = maxFederalPellGrant + potentialSubsidizedLoan + potentialUnsubsidizedLoan + meritScholarshipPotential + institutionalGrantPotential;\n    totalAidEligibility = Math.min(totalAidEligibility, costOfAttendance); // Total aid should not exceed COA\n    totalAidEligibility = Math.round(Math.max(0, totalAidEligibility));\n\n    return {\n        expectedFamilyContribution: expectedFamilyContribution,\n        financialNeed: financialNeed,\n        maxFederalPellGrant: maxFederalPellGrant,\n        maxFederalStudentLoan: maxFederalStudentLoan,\n        meritScholarshipPotential: meritScholarshipPotential,\n        totalAidEligibility: totalAidEligibility\n    };\n}",
  "summary": "Helps students and families estimate and optimize their eligibility for various grants, scholarships, and federal loans based on household financial data and academic profiles.",
  "cta": "Optimize Your Student Aid Eligibility Now",
  "faq": [
    {
      "q": "What is the Expected Family Contribution (EFC) and how does it affect aid?",
      "a": "The EFC (or Student Aid Index - SAI - as it's being rebranded) is a number that colleges use to determine how much financial aid you are eligible to receive. It's an index of your family's financial strength and represents the amount a family can reasonably be expected to contribute toward one year of college costs. The lower your EFC, the more need-based aid you're likely to receive."
    },
    {
      "q": "How is 'Financial Need' calculated?",
      "a": "Financial Need is determined by subtracting your Expected Family Contribution (EFC) from the college's Cost of Attendance (COA). If your COA is $40,000 and your EFC is $10,000, your financial need is $30,000. Colleges then try to meet this need through a combination of grants, scholarships, and loans."
    },
    {
      "q": "What's the difference between grants, scholarships, and federal loans?",
      "a": "Grants and scholarships are 'gift aid' – money you don't have to pay back. Grants are typically need-based, while scholarships are often merit-based (academic, athletic, artistic, etc.). Federal loans are money you borrow from the government that must be repaid, often with interest, but usually offer more favorable terms than private loans."
    },
    {
      "q": "Does my GPA or SAT/ACT score significantly impact my aid eligibility?",
      "a": "Yes, primarily for merit-based scholarships. Many colleges and external organizations offer scholarships to students with strong academic records (high GPA, good test scores). While GPA/scores don't directly affect federal need-based aid calculations (like Pell Grants), they are crucial for unlocking significant non-repayable funds."
    },
    {
      "q": "What is 'Cost of Attendance' (COA) and why is it important?",
      "a": "The Cost of Attendance (COA) is the total amount it will cost to attend a college for one academic year. It includes tuition and fees, room and board, books and supplies, transportation, and personal expenses. COA is the foundation for determining your financial need; it represents the maximum amount of financial aid you can receive from all sources."
    },
    {
      "q": "How does student dependency status (dependent vs. independent) affect aid calculations?",
      "a": "Dependency status is critical. Dependent students must report parental income and assets on the FAFSA, which heavily influences their EFC. Independent students only report their own (and spouse's, if applicable) income and assets, often resulting in a lower EFC and higher need-based aid eligibility."
    },
    {
      "q": "Is this tool a substitute for completing the official FAFSA or CSS Profile?",
      "a": "No. This tool provides an *estimate* based on simplified formulas. The official Free Application for Federal Student Aid (FAFSA) and, for some private colleges, the CSS Profile, are the only ways to apply for federal, state, and institutional financial aid. Always complete these official applications accurately and on time."
    },
    {
      "q": "What are the next steps after using this optimizer?",
      "a": "After getting an estimate, your next steps should include: 1. Completing the FAFSA (and CSS Profile if required by your target schools). 2. Researching specific college aid policies and scholarship opportunities. 3. Exploring state-specific aid programs. 4. Consulting a financial aid advisor for personalized guidance. 5. Comparing financial aid offers from different institutions carefully."
    }
  ],
  "tags": [
    "student aid",
    "financial aid",
    "FAFSA",
    "EFC",
    "SAI",
    "scholarships",
    "grants",
    "student loans",
    "college planning",
    "higher education finance",
    "tuition costs",
    "financial planning"
  ],
  "related": [
    "college-roi-calculator",
    "student-loan-repayment-planner",
    "tuition-savings-estimator",
    "fafsa-sai-estimator"
  ],
  "article": [
    {
      "heading": "The Importance of the Student Aid Eligibility Optimizer in Modern Context",
      "body": "Navigating the labyrinthine world of higher education finance has become an increasingly daunting task for students and their families. With tuition fees escalating year after year, and the cost of attendance frequently outstripping inflation, securing adequate financial aid is no longer a luxury but a fundamental necessity for millions pursuing college degrees. The \"Student Aid Eligibility Optimizer\" is designed to bring clarity and proactive planning to this critical process, serving as an indispensable resource in today's complex educational landscape.\n\nThe demand for transparent and optimized financial planning for higher education is evergreen. Families are constantly seeking tools that can demystify the aid application process, providing actionable insights long before official applications are due. The traditional approach, often involving a reactive response to financial aid offers after college acceptances, can leave families feeling overwhelmed and regretful about missed opportunities. Our optimizer addresses this by empowering users with an early, comprehensive estimate of their potential eligibility for various forms of aid—grants, scholarships, and federal loans—allowing for strategic decision-making.\n\nThe landscape of financial aid itself is dynamic, with federal policy changes, shifting institutional priorities, and an ever-growing array of private scholarships. For instance, the recent FAFSA Simplification Act has introduced new terminology like the Student Aid Index (SAI) replacing EFC, and altered calculation methodologies. Such changes, while intended to streamline the process, often create initial confusion. A tool that can quickly adapt and provide estimates based on current principles, even simplified ones, becomes a beacon of guidance.\n\nFurthermore, the psychological burden of financing higher education can be immense. Students might self-select out of applying to certain institutions perceived as 'too expensive,' without fully understanding the aid they might qualify for. Parents might delay retirement savings to prioritize college funds, or conversely, take on unsustainable debt. By providing a clear, early estimate of aid eligibility, this optimizer can alleviate some of this stress, enabling families to set realistic expectations, explore a wider range of institutions, and engage in healthier long-term financial planning. It shifts the paradigm from reactive worry to proactive optimization, ensuring that the dream of higher education remains attainable and financially sound."
    },
    {
      "heading": "In-Depth Technical Guide: How the Calculation Works",
      "body": "The Student Aid Eligibility Optimizer employs a multi-faceted, yet simplified, approach to estimate potential financial aid. While not a direct substitute for the official FAFSA or CSS Profile, it mirrors key methodologies to provide a robust and indicative projection. The calculation primarily revolves around determining your Estimated Expected Family Contribution (EFC), which is the cornerstone of need-based aid.\n\n**Step 1: Calculating the Expected Family Contribution (EFC)**\nOur EFC estimation differentiates between dependent and independent students, as this status profoundly impacts the inputs considered. For dependent students, both parent and student income and assets are evaluated. For independent students, only their own (and spouse's) financial data is used.\n\n*   **Parental Contribution from Income:** We start with the Parent(s) Adjusted Gross Income (AGI). From this, a 'Parent Income Protection Allowance' (IPA) is deducted. This allowance, which increases with family size, shields a portion of income deemed necessary for basic living expenses. The remaining disposable income is then subjected to a simplified tiered contribution rate (e.g., 22% on the first $30,000, escalating to higher percentages for higher income brackets). This tiered system ensures that those with greater financial capacity contribute a larger proportion.\n*   **Parental Contribution from Assets:** Similar to income, a 'Parent Asset Protection Allowance' (APA) is subtracted from non-retirement assets (savings, investments). This allowance protects a portion of assets. The remaining net assets are then multiplied by a fixed contribution rate (approximately 5.64% in real FAFSA calculations). Crucially, if there are multiple college students in the household, the combined parental contribution (from both income and assets) is divided by the number of students, thereby reducing the EFC per student and increasing their potential aid.\n*   **Student Contribution from Income:** Students also have an 'Income Protection Allowance' deducted from their AGI. Any income above this allowance is typically assessed at a higher contribution rate (e.g., 50%), reflecting the expectation that students should contribute more proportionally from their own earnings.\n*   **Student Contribution from Assets:** Student assets are generally assessed at a higher rate (e.g., 20%) than parental assets, as they are considered more readily available for college expenses.\n\nAll these contributions are summed to arrive at the total Estimated EFC. The EFC is then capped at zero if the calculations result in a negative value, reflecting that no family contribution is expected.\n\n**Step 2: Determining Financial Need**\nOnce the EFC is established, the Financial Need is calculated by a straightforward subtraction: `Cost of Attendance (COA) - Expected Family Contribution (EFC)`. The COA includes tuition, fees, room, board, books, and other expenses. A higher financial need indicates greater eligibility for need-based aid.\n\n**Step 3: Estimating Federal Pell Grant Eligibility**\nThe Federal Pell Grant is a cornerstone of federal financial aid, primarily for undergraduate students demonstrating exceptional financial need. Our optimizer estimates Pell eligibility based on the calculated EFC. Typically, a Pell Grant is awarded to students with an EFC below a certain threshold, with the maximum grant reserved for those with an EFC of zero.\n\n**Step 4: Projecting Federal Student Loan Eligibility**\nFederal student loans (Subsidized and Unsubsidized) have annual limits based on a student's year in college and dependency status. For simplicity, our tool uses first-year undergraduate caps. Subsidized loans are limited by financial need, meaning the government pays the interest while the student is in school. Unsubsidized loans are not need-based, and interest accrues immediately. The tool calculates the maximum potential for both, ensuring that the combined loan amount does not exceed the remaining COA after other aid.\n\n**Step 5: Assessing Merit Scholarship Potential**\nMerit scholarships are distinct from need-based aid and are awarded based on academic achievements (GPA, test scores), talents, or other criteria. Our optimizer provides an estimated merit scholarship potential using a simplified tiered system for GPA and an additional factor for SAT/ACT scores. This helps students understand the value of their academic profile beyond just admissions.\n\n**Step 6: Total Estimated Aid Eligibility**\nFinally, the tool aggregates all estimated aid components: Pell Grants, Federal Student Loans (Subsidized and Unsubsidized), and Merit Scholarships. A simplified estimate for institutional need-based grants is also included, often as a percentage of the remaining financial need not covered by federal grants or subsidized loans. The total aid is capped at the COA, ensuring that over-awarding does not occur in the estimation. This comprehensive sum provides a powerful projection of the total financial assistance a student might expect."
    },
    {
      "heading": "Real-World Application Scenarios",
      "body": "The Student Aid Eligibility Optimizer is a versatile tool, offering profound value across a spectrum of real-world scenarios for diverse student and family profiles. Here are a few examples:\n\n**Scenario 1: The High-Achieving Student from a Middle-Income Family**\n*   **Persona:** Sarah is a senior in high school with a 3.9 GPA, a strong SAT score, and a passion for engineering. Her parents have a combined AGI of $120,000 and have saved $70,000 for retirement but have about $30,000 in a general savings account. They worry they make 'too much' for need-based aid but not enough to comfortably afford a top-tier university with a COA of $70,000. Sarah also feels pressure to perform well academically to secure merit scholarships, fearing she'll fall into the 'middle-income trap.'\n*   **Optimizer's Role:** Sarah uses the optimizer. She inputs her family's financial data and her excellent academic profile. The tool estimates her EFC to be around $35,000 (after considering parent income, assets, and dividing by one college student). This immediately shows a financial need of $35,000 ($70,000 COA - $35,000 EFC). More importantly, her strong GPA and SAT score translate into an estimated $15,000 - $20,000 in merit scholarship potential. Combined with federal loans and a potential institutional grant based on need, the optimizer projects total aid eligibility of approximately $45,000. This provides immense relief, showing Sarah that with significant merit aid and some need-based assistance, her dream school might be within reach, reducing the out-of-pocket cost to a manageable level ($25,000 - $30,000). It helps her confidently apply and negotiate aid offers.\n\n**Scenario 2: The First-Generation Student from a Lower-Income Family**\n*   **Persona:** Miguel is a bright student, the first in his family considering college. His parents' AGI is $35,000, and they have minimal assets. Miguel works part-time, earning about $5,000 annually, and has $1,000 in savings. The idea of college costs, even at a state university with a COA of $25,000, seems insurmountable to his family. They are unfamiliar with the aid process.\n*   **Optimizer's Role:** Miguel uses the optimizer. His family's low income and assets, combined with his modest earnings, result in an estimated EFC near $0. This immediately flags a high financial need of $25,000. The optimizer projects maximum Federal Pell Grant eligibility (around $7,395), along with substantial federal subsidized and unsubsidized loan eligibility (e.g., $5,500). Even with an average GPA, the tool shows a significant portion of his COA potentially covered by federal and institutional need-based aid (e.g., $7,395 Pell + $5,500 Loans + $5,000 Institutional Grant, totaling around $17,895). This demystifies the process, showing Miguel's family that they won't have to bear the full cost and that college is a realistic aspiration. It empowers them to apply for FAFSA confidently and explore state grants.\n\n**Scenario 3: Family Planning for Multiple Children Attending College**\n*   **Persona:** The Chen family has two children, one entering college next year and another two years later. Their combined AGI is $150,000, and they have $150,000 in non-retirement assets. They are concerned about managing two college tuitions simultaneously, with COAs potentially around $45,000 each. They want to understand how having multiple children in college impacts aid.\n*   **Optimizer's Role:** The Chens first run the optimizer for their first child, inputting '1' for college students. The EFC is relatively high. They then re-run the optimizer, changing 'Number of College Students in Household' to '2'. The tool demonstrates a significant reduction in the EFC *per student* because the parental contribution is divided among more recipients. This insight is crucial: while their overall financial contribution remains the same, the 'expected family contribution per student' drastically decreases, potentially unlocking more need-based aid for both children than they initially anticipated. This helps them adjust their savings strategy, potentially allowing for more aggressive aid applications rather than solely relying on their savings, and manage their cash flow more effectively over the years their children are in college."
    },
    {
      "heading": "Advanced Considerations and Potential Pitfalls",
      "body": "While the Student Aid Eligibility Optimizer provides invaluable early insights, it's crucial to understand its limitations and consider advanced aspects of financial aid:\n\n**1. Simplified EFC vs. Official FAFSA/CSS Profile:** Our optimizer uses a simplified methodology to provide quick estimates. The actual FAFSA (and the Student Aid Index/SAI replacing EFC in future cycles) and the CSS Profile are far more complex. The FAFSA employs specific income exclusions, asset calculations, and allowances (e.g., different asset protection allowances based on parental age, specific business asset exclusions) that are not fully replicated here. The CSS Profile, used by many private institutions, dives even deeper, often considering home equity, retirement savings, and other discretionary expenses not typically on the FAFSA. Always complete the official forms accurately.\n\n**2. Institutional Aid Variations:** Colleges are not obligated to meet 100% of a student's demonstrated financial need. Even among schools that promise to meet full need, the 'aid package' can vary significantly in its composition (more grants vs. more loans). Furthermore, institutional need-based grants often have specific criteria beyond federal EFC, such as GPA thresholds, state residency, or specific program enrollment. Our institutional grant estimate is a broad approximation.\n\n**3. State-Specific Aid Programs:** Many states offer their own grant and scholarship programs, often with unique eligibility requirements (e.g., residency, specific academic performance, enrollment at in-state institutions). These are not accounted for in this general optimizer. Students should always research their state's higher education agency for specific opportunities.\n\n**4. Special Circumstances:** Life events can significantly alter a family's financial situation after aid applications are submitted (e.g., job loss, medical expenses, divorce, death of a parent). Neither this optimizer nor the initial FAFSA application can fully capture these nuances. Students experiencing special circumstances should contact the financial aid office of their prospective colleges to request a professional judgment review, which can lead to adjustments in their aid eligibility.\n\n**5. Merit Aid Specifics:** While the optimizer gives a general sense of merit scholarship potential based on GPA and test scores, actual merit aid awards are highly institutional and competitive. Factors like major, extracurricular activities, essays, and even an applicant's 'fit' with the institution can play a significant role. Some scholarships are also 'stackable,' while others may not be, potentially impacting total aid.\n\n**6. Loan Types and Terms:** Our tool estimates general federal loan eligibility. However, there are different types of federal loans (Direct Subsidized, Direct Unsubsidized, PLUS Loans for parents/graduates), each with distinct interest rates, repayment terms, and origination fees. Private loans, not covered by this optimizer, should generally be a last resort due to less favorable terms.\n\n**7. Timeliness:** Financial aid is often awarded on a first-come, first-served basis, especially for limited institutional and state funds. Using this optimizer early is a proactive step, but the actual application forms (FAFSA/CSS Profile) must be completed as soon as they become available to maximize chances.\n\nIn essence, use this optimizer as a powerful preliminary planning tool, but always follow up with official applications and direct communication with financial aid offices. It’s a compass, not the entire map."
    }
  ]
}
